{
  "daily": {
    "MES": {
      "trend": "down",
      "pips": 328.43,
      "usd": null,
      "pct": -1.05
    },
    "MNQ": {
      "trend": "down",
      "pips": 1720.5,
      "usd": null,
      "pct": -1.41
    },
    "MYM": {
      "trend": "down",
      "pips": 584.64,
      "usd": null,
      "pct": -0.62
    },
    "M2K": {
      "trend": "down",
      "pips": 469.21,
      "usd": null,
      "pct": -1.24
    },
    "MGC": {
      "trend": "down",
      "pips": 1764.29,
      "usd": null,
      "pct": -0.5
    },
    "SIL": {
      "trend": "up",
      "pips": 2100.99,
      "usd": null,
      "pct": 0.77
    },
    "MHG": {
      "trend": "down",
      "pips": 347.0,
      "usd": null,
      "pct": -2.92
    },
    "MCL": {
      "trend": "down",
      "pips": 222.29,
      "usd": null,
      "pct": -4.23
    },
    "MNG": {
      "trend": "down",
      "pips": 1107.64,
      "usd": null,
      "pct": -15.18
    },
    "ES": {
      "trend": "down",
      "pips": 328.43,
      "usd": null,
      "pct": -1.05
    },
    "NQ": {
      "trend": "down",
      "pips": 1720.5,
      "usd": null,
      "pct": -1.41
    },
    "YM": {
      "trend": "down",
      "pips": 584.64,
      "usd": null,
      "pct": -0.62
    },
    "RTY": {
      "trend": "down",
      "pips": 469.21,
      "usd": null,
      "pct": -1.24
    },
    "GC": {
      "trend": "down",
      "pips": 1764.29,
      "usd": null,
      "pct": -0.5
    },
    "SI": {
      "trend": "up",
      "pips": 2100.99,
      "usd": null,
      "pct": 0.77
    },
    "HG": {
      "trend": "down",
      "pips": 347.0,
      "usd": null,
      "pct": -2.92
    },
    "CL": {
      "trend": "down",
      "pips": 222.29,
      "usd": null,
      "pct": -4.23
    },
    "NG": {
      "trend": "down",
      "pips": 1107.64,
      "usd": null,
      "pct": -15.18
    },
    "RB": {
      "trend": "down",
      "pips": 548.29,
      "usd": null,
      "pct": -2.24
    },
    "HO": {
      "trend": "down",
      "pips": 1325.36,
      "usd": null,
      "pct": -11.64
    },
    "PL": {
      "trend": "down",
      "pips": 1393.86,
      "usd": null,
      "pct": -1.48
    },
    "ZT": {
      "trend": "flat",
      "pips": 10.18,
      "usd": null,
      "pct": 0.01
    },
    "ZF": {
      "trend": "flat",
      "pips": 28.57,
      "usd": null,
      "pct": 0.03
    },
    "ZN": {
      "trend": "flat",
      "pips": 22.93,
      "usd": null,
      "pct": 0.01
    },
    "ZB": {
      "trend": "down",
      "pips": 26.43,
      "usd": null,
      "pct": -0.19
    },
    "UB": {
      "trend": "down",
      "pips": 34.14,
      "usd": null,
      "pct": -0.19
    },
    "TN": {
      "trend": "flat",
      "pips": 30.07,
      "usd": null,
      "pct": -0.01
    },
    "ZC": {
      "trend": "down",
      "pips": 21.57,
      "usd": null,
      "pct": -0.7
    },
    "ZW": {
      "trend": "down",
      "pips": 40.86,
      "usd": null,
      "pct": -1.07
    },
    "ZS": {
      "trend": "down",
      "pips": 54.57,
      "usd": null,
      "pct": -0.78
    },
    "ZM": {
      "trend": "down",
      "pips": 47.43,
      "usd": null,
      "pct": -0.17
    },
    "ZL": {
      "trend": "down",
      "pips": 108.21,
      "usd": null,
      "pct": -1.48
    },
    "6A": {
      "trend": "down",
      "pips": 62.21,
      "usd": null,
      "pct": -0.4
    },
    "6B": {
      "trend": "down",
      "pips": 79.86,
      "usd": null,
      "pct": -0.1
    },
    "6C": {
      "trend": "down",
      "pips": 74.57,
      "usd": null,
      "pct": -0.29
    },
    "6E": {
      "trend": "up",
      "pips": 180.43,
      "usd": null,
      "pct": 0.12
    },
    "6J": {
      "trend": "down",
      "pips": 118.5,
      "usd": null,
      "pct": -0.08
    },
    "6S": {
      "trend": "down",
      "pips": 139.89,
      "usd": null,
      "pct": -0.1
    },
    "6N": {
      "trend": "down",
      "pips": 59.04,
      "usd": null,
      "pct": -0.27
    },
    "6M": {
      "trend": "down",
      "pips": 3.42,
      "usd": null,
      "pct": -0.73
    }
  },
  "hourly": {
    "MES": {
      "trend": "down",
      "pips": 121.0,
      "usd": null,
      "pct": -0.2
    },
    "MNQ": {
      "trend": "down",
      "pips": 606.21,
      "usd": null,
      "pct": -0.23
    },
    "MYM": {
      "trend": "down",
      "pips": 181.79,
      "usd": null,
      "pct": -0.14
    },
    "M2K": {
      "trend": "down",
      "pips": 162.5,
      "usd": null,
      "pct": -0.27
    },
    "MGC": {
      "trend": "down",
      "pips": 1317.86,
      "usd": null,
      "pct": -0.9
    },
    "SIL": {
      "trend": "down",
      "pips": 1243.06,
      "usd": null,
      "pct": -2.22
    },
    "MHG": {
      "trend": "down",
      "pips": 208.14,
      "usd": null,
      "pct": -0.67
    },
    "MCL": {
      "trend": "flat",
      "pips": 81.64,
      "usd": null,
      "pct": 0.02
    },
    "MNG": {
      "trend": "down",
      "pips": 143.43,
      "usd": null,
      "pct": -0.59
    },
    "ES": {
      "trend": "down",
      "pips": 121.0,
      "usd": null,
      "pct": -0.2
    },
    "NQ": {
      "trend": "down",
      "pips": 606.21,
      "usd": null,
      "pct": -0.23
    },
    "YM": {
      "trend": "down",
      "pips": 181.79,
      "usd": null,
      "pct": -0.14
    },
    "RTY": {
      "trend": "down",
      "pips": 162.5,
      "usd": null,
      "pct": -0.27
    },
    "GC": {
      "trend": "down",
      "pips": 1317.86,
      "usd": null,
      "pct": -0.9
    },
    "SI": {
      "trend": "down",
      "pips": 1243.06,
      "usd": null,
      "pct": -2.22
    },
    "HG": {
      "trend": "down",
      "pips": 208.14,
      "usd": null,
      "pct": -0.67
    },
    "CL": {
      "trend": "flat",
      "pips": 81.64,
      "usd": null,
      "pct": 0.02
    },
    "NG": {
      "trend": "down",
      "pips": 143.43,
      "usd": null,
      "pct": -0.59
    },
    "RB": {
      "trend": "up",
      "pips": 196.71,
      "usd": null,
      "pct": 0.11
    },
    "HO": {
      "trend": "up",
      "pips": 325.43,
      "usd": null,
      "pct": 0.34
    },
    "PL": {
      "trend": "up",
      "pips": 823.0,
      "usd": null,
      "pct": 0.08
    },
    "ZT": {
      "trend": "flat",
      "pips": 3.04,
      "usd": null,
      "pct": 0.01
    },
    "ZF": {
      "trend": "flat",
      "pips": 7.5,
      "usd": null,
      "pct": 0.03
    },
    "ZN": {
      "trend": "up",
      "pips": 6.29,
      "usd": null,
      "pct": 0.06
    },
    "ZB": {
      "trend": "up",
      "pips": 7.5,
      "usd": null,
      "pct": 0.11
    },
    "UB": {
      "trend": "up",
      "pips": 8.93,
      "usd": null,
      "pct": 0.11
    },
    "TN": {
      "trend": "up",
      "pips": 8.0,
      "usd": null,
      "pct": 0.05
    },
    "ZC": {
      "trend": "down",
      "pips": 5.14,
      "usd": null,
      "pct": -0.06
    },
    "ZW": {
      "trend": "flat",
      "pips": 11.0,
      "usd": null,
      "pct": 0.0
    },
    "ZS": {
      "trend": "flat",
      "pips": 14.71,
      "usd": null,
      "pct": -0.02
    },
    "ZM": {
      "trend": "down",
      "pips": 10.43,
      "usd": null,
      "pct": -0.1
    },
    "ZL": {
      "trend": "up",
      "pips": 28.86,
      "usd": null,
      "pct": 0.06
    },
    "6A": {
      "trend": "flat",
      "pips": 28.43,
      "usd": null,
      "pct": 0.01
    },
    "6B": {
      "trend": "flat",
      "pips": 30.71,
      "usd": null,
      "pct": 0.01
    },
    "6C": {
      "trend": "flat",
      "pips": 37.07,
      "usd": null,
      "pct": 0.0
    },
    "6E": {
      "trend": "flat",
      "pips": 48.93,
      "usd": null,
      "pct": 0.04
    },
    "6J": {
      "trend": "up",
      "pips": 36.36,
      "usd": null,
      "pct": 0.06
    },
    "6S": {
      "trend": "up",
      "pips": 29.79,
      "usd": null,
      "pct": 0.08
    },
    "6N": {
      "trend": "flat",
      "pips": 20.04,
      "usd": null,
      "pct": 0.02
    },
    "6M": {
      "trend": "flat",
      "pips": 2.04,
      "usd": null,
      "pct": -0.04
    }
  },
  "_meta": {
    "updated_utc": "2026-02-02T03:47:36.878237Z",
    "source": "Yahoo Finance via yfinance",
    "atr_period": 14
  }
}